ukw_intelli_store/__init__.py
ukw_intelli_store/__main__.py
ukw_intelli_store/cli.py
ukw_intelli_store/config.py
ukw_intelli_store/endomaterial.py
ukw_intelli_store/utils.py
ukw_intelli_store-0.0.1.dist-info/AUTHORS.rst
ukw_intelli_store-0.0.1.dist-info/LICENSE
ukw_intelli_store-0.0.1.dist-info/METADATA
ukw_intelli_store-0.0.1.dist-info/WHEEL
ukw_intelli_store-0.0.1.dist-info/entry_points.txt
ukw_intelli_store-0.0.1.dist-info/top_level.txt
ukw_intelli_store-0.0.1.dist-info/RECORD
