Metadata-Version: 2.1
Name: ukw-intelli-store
Version: 0.0.1
Summary: Package to read and explore material consumption
Home-page: https://github.com/Maddonix/ukw-intelli-store
Author: Thomas J. Lux
Author-email: tlux14@googlemail.com
License: MIT
Project-URL: Documentation, https://ukw-intelli-store.readthedocs.io/
Project-URL: Changelog, https://ukw-intelli-store.readthedocs.io/en/latest/changelog.html
Project-URL: Issue Tracker, https://github.com/Maddonix/ukw-intelli-store/issues
Platform: UNKNOWN
Classifier: Development Status :: 5 - Production/Stable
Classifier: Intended Audience :: Developers
Classifier: License :: OSI Approved :: MIT License
Classifier: Operating System :: Unix
Classifier: Operating System :: POSIX
Classifier: Operating System :: Microsoft :: Windows
Classifier: Programming Language :: Python
Classifier: Programming Language :: Python :: 3
Classifier: Programming Language :: Python :: 3 :: Only
Classifier: Programming Language :: Python :: 3.6
Classifier: Programming Language :: Python :: 3.7
Classifier: Programming Language :: Python :: 3.8
Classifier: Programming Language :: Python :: 3.9
Classifier: Programming Language :: Python :: Implementation :: CPython
Classifier: Programming Language :: Python :: Implementation :: PyPy
Classifier: Topic :: Utilities
Requires-Python: >=3.6
Requires-Dist: pandas
Requires-Dist: numpy
Requires-Dist: openpyxl
Requires-Dist: xlrd
